{
  "usuario": "ranet101",
  "cromos": [
    {
      "id": 634,
      "nombre": "DB-022",
      "cantidad": 1
    },
    {
      "id": 128,
      "nombre": "Faker",
      "cantidad": 1
    },
    {
      "id": 421,
      "nombre": "mei2",
      "cantidad": 1
    },
    {
      "id": 645,
      "nombre": "DB-033",
      "cantidad": 1
    },
    {
      "id": 787,
      "nombre": "DOS-CARAS",
      "cantidad": 1
    },
    {
      "id": 338,
      "nombre": "Shiryū de Dragón",
      "cantidad": 1
    },
    {
      "id": 551,
      "nombre": "BARRACUS-JAIL",
      "cantidad": 1
    },
    {
      "id": 842,
      "nombre": "GUILE2",
      "cantidad": 1
    },
    {
      "id": 814,
      "nombre": "MILENNA",
      "cantidad": 1
    },
    {
      "id": 181,
      "nombre": "Hydro man",
      "cantidad": 1
    },
    {
      "id": 596,
      "nombre": "K.HEINZ-SCHENEIDER",
      "cantidad": 2
    },
    {
      "id": 765,
      "nombre": "Finster",
      "cantidad": 1
    },
    {
      "id": 824,
      "nombre": "SINDEL",
      "cantidad": 1
    },
    {
      "id": 860,
      "nombre": "MAHONEY-JAIL",
      "cantidad": 1
    },
    {
      "id": 791,
      "nombre": "GORDON",
      "cantidad": 1
    },
    {
      "id": 189,
      "nombre": "Shocker",
      "cantidad": 1
    },
    {
      "id": 276,
      "nombre": "Baxter",
      "cantidad": 1
    },
    {
      "id": 781,
      "nombre": "BATGIRL",
      "cantidad": 1
    },
    {
      "id": 847,
      "nombre": "RYU",
      "cantidad": 1
    },
    {
      "id": 834,
      "nombre": "CAMMY",
      "cantidad": 1
    },
    {
      "id": 99,
      "nombre": "Demona",
      "cantidad": 1
    },
    {
      "id": 946,
      "nombre": "SLOTH-JAIL",
      "cantidad": 1
    },
    {
      "id": 535,
      "nombre": "Venkman-Jail",
      "cantidad": 1
    },
    {
      "id": 291,
      "nombre": "Zorax",
      "cantidad": 1
    },
    {
      "id": 534,
      "nombre": "T800-Jail",
      "cantidad": 1
    },
    {
      "id": 172,
      "nombre": "May Parker",
      "cantidad": 1
    },
    {
      "id": 440,
      "nombre": "scrabs",
      "cantidad": 1
    },
    {
      "id": 744,
      "nombre": "Dark-Deathmask-de-Cancer",
      "cantidad": 1
    },
    {
      "id": 499,
      "nombre": "seed",
      "cantidad": 1
    },
    {
      "id": 357,
      "nombre": "china",
      "cantidad": 1
    },
    {
      "id": 324,
      "nombre": "Wolverine",
      "cantidad": 1
    },
    {
      "id": 762,
      "nombre": "bkue",
      "cantidad": 1
    },
    {
      "id": 58,
      "nombre": "rey romos",
      "cantidad": 1
    },
    {
      "id": 849,
      "nombre": "SAGAT",
      "cantidad": 1
    },
    {
      "id": 555,
      "nombre": "INDIANA-JONES-JAIL",
      "cantidad": 1
    },
    {
      "id": 456,
      "nombre": "boman",
      "cantidad": 1
    },
    {
      "id": 913,
      "nombre": "SUPERGIRL",
      "cantidad": 1
    },
    {
      "id": 931,
      "nombre": "RANDY-ORTON",
      "cantidad": 1
    }
  ]
}